ovrl_sdk/__init__.py
ovrl_sdk/client.py
ovrl_sdk/config.py
ovrl_sdk/constants.py
ovrl_sdk/exceptions.py
ovrl_sdk/soroban.py
ovrl_sdk/types.py
ovrl_sdk-0.1.0.dist-info/METADATA
ovrl_sdk-0.1.0.dist-info/WHEEL
ovrl_sdk-0.1.0.dist-info/licenses/LICENSE
ovrl_sdk-0.1.0.dist-info/RECORD
