Metadata-Version: 2.4
Name: ovrl-sdk
Version: 0.1.0
Summary: Async SDK for OVRL on Stellar/Soroban with bootstrap, quoting, monitoring, and contract helpers
Project-URL: Homepage, https://github.com/overlumens/ovrl-sdk
Project-URL: Repository, https://github.com/overlumens/ovrl-sdk
Project-URL: Documentation, https://overlumens.github.io/ovrl-sdk/
Author-email: "Overlumens (github.com/overlumens)" <support@overlumens.com>, "Md Mahedi Zaman Zaber (github.com/zaber-dev)" <zaber@overlumens.com>
License: Apache-2.0
License-File: LICENSE
Requires-Python: >=3.10
Requires-Dist: aiohttp>=3.9.0
Requires-Dist: stellar-sdk[aiohttp]>=11.0.0
Provides-Extra: dev
Requires-Dist: pytest-asyncio>=0.23; extra == 'dev'
Requires-Dist: pytest-mock>=3.12; extra == 'dev'
Requires-Dist: pytest>=8.2; extra == 'dev'
Requires-Dist: sphinxawesome-theme>=5.1; extra == 'dev'
